fast_queue/__init__.py
fast_queue-0.0.3.dist-info/DESCRIPTION.rst
fast_queue-0.0.3.dist-info/METADATA
fast_queue-0.0.3.dist-info/RECORD
fast_queue-0.0.3.dist-info/WHEEL
fast_queue-0.0.3.dist-info/metadata.json
fast_queue-0.0.3.dist-info/top_level.txt
