Metadata-Version: 2.0
Name: fast-queue
Version: 0.0.3
Summary: Simple Task Producer
Home-page: http://github.com/gutomaia/fast_queue/
Author: Gustavo Maia Neto (Guto Maia)
Author-email: guto@guto.net
License: MIT
Keywords: celery queue
Platform: UNKNOWN
Classifier: Development Status :: 3 - Alpha
Classifier: Programming Language :: Python :: 2.7
Classifier: License :: OSI Approved :: MIT License
Requires-Dist: six
Requires-Dist: kombu
